abstract_test_package/__init__.py
abstract_test_package/main.py
abstract_test_package/test.py
abstract_test_package/test_module.py
abstract_test_package-0.0.53.dist-info/METADATA
abstract_test_package-0.0.53.dist-info/WHEEL
abstract_test_package-0.0.53.dist-info/top_level.txt
abstract_test_package-0.0.53.dist-info/RECORD
