Metadata-Version: 2.4
Name: abstract_test_package
Version: 0.0.53
Summary: abstract_test_package is a Python package that facilitates testing with abstract scenarios. Utilizing PyTest, it offers extra utilities to streamline the creation and execution of abstract tests.
Home-page: https://github.com/AbstractEndeavors/abstract_test_package
Author: putkoff
Author-email: partners@abstractendeavors.com
Classifier: Development Status :: 3 - Alpha
Classifier: Intended Audience :: Developers
Classifier: License :: OSI Approved :: MIT License
Classifier: Programming Language :: Python :: 3
Classifier: Programming Language :: Python :: 3.11
Classifier: Operating System :: OS Independent
Requires-Python: >=3.6
Dynamic: author
Dynamic: author-email
Dynamic: classifier
Dynamic: description
Dynamic: description-content-type
Dynamic: home-page
Dynamic: requires-python
Dynamic: summary
